<tool id="IMa3" name="Run IMa3">
  <description>IMa3 Run</description>

  <command>
    home/asethuraman/IMa3/IMa3_singlecpu -i $input -o output.out -q$q -m$m -t$t -b$b -l$l -s$s -hn$hn -ha$ha -hb$hb $p $r -z$z> $output2</command>
  <inputs>
    <param name="np" type="integer" value="1" label="Number of processors to run in parallel (Max. 8)" max="8" />
    <param name="input" type="data" label="Input file name"/>
    <param name="q" type="float" value="0" size="1" label="Prior for Ne" />
    <param name="m" type="float" value="0" size="1" label="Prior for Migration rate" />
    <param name="t" type="float"  value="0" size="1" label="Prior for divergence time"  />
    <param name="b" type="integer"  value="0" size="1" label="Number of burn-in steps" />
    <param name="l" type="integer"  value="0" size="1" label="Number of genealogies to save post burn-in" />
    <param name="d" type="integer" label="Number of steps between genealogy saving (MCMC mode only)(default 100)" value="100" />
    <param name="s" type="integer"  value="0" size="1" label="Random number seed" />
    <param name="hn" type="integer"  value="0" size="1" label="Number of MCMC chains" />
    <param name="ha" type="float"  value="0" size="1" label="First heating parameter"  />
    <param name="hb" type="float"  value="0" size="1" label="Second heating parameter"  />
    <param name="p" type="select" label="Output options" display="radio" multiple="false" >
      <option value="-p0">0 Turn off trend plots in outfile (default is to print trend plots)</option>
      <option value="-p1">1 Turn off plots of marginal curves in outfile (default is to print marginal density plots) </option>
      <option value="-p2">2 Print TMRCA histogram for each genealogy (MCMC mode only) </option>
      <option value="-p3">3 Print histogram of splitting times divided by prior (do not use with -j0 or when only 2 sampled populations </option>
      <option value="-p4">4 Turn off printing of 2Nm values </option>
      <option value="-p5">5 Print pairwise probabilities that one parameter is greater than another </option>
      <option value="-p6">6 Print estimates and histograms of population migration rate </option>
      <option value="-p7">7 Print joint estimate for splitting times (MCMC mode only, for models with 3, 4 or 5 populations) </option>
   </param>
   <param name="r" type="select" label="Run options" display="radio" multiple="false">
      <option value="-r1">1 Do not save genealogies to a file (default saves sampled genealogies)</option>
      <option value="-r2">2 Save the state of the Markov chain in a file - named with extension .mcf (MCMC mode only)</option>
      <option value="-r4">4 Write all mutation related updates rates to stdout during the run (default is to suppress this)</option>
      <option value="-r5">5 Print burntrend file at end of burnin period; use with -b followed by integer (MCMC mode only)</option>
   </param>
   <param name="z" type="integer" label="Number of steps between screen output (default is 10000) (MCMC mode only)" value="10000" />
  </inputs>

  <outputs>
    <data name="output1" format="text" label="Output file produced by IMa3" from_work_dir="output.out"/>
    <data name="output2" format="text" label="Screen output during run" />
		
   </outputs>

  <help>
    **IMa3** is a parallel implementation of IMa3, using OpenMPI-C++ - a Bayesian MCMC based method for inferring population demography under the IM (Isolation with Migration) model.
  </help>

  <citations>
    <citation type="doi">10.1111/1755-0998.12437</citation>
    <citation type="doi">10.1093/molbev/msy162</citation>	  
  </citations>

</tool>
